py_progress/__init__.py
py_progress/progress.py
py_progress_lib-0.8.5.dist-info/METADATA
py_progress_lib-0.8.5.dist-info/WHEEL
py_progress_lib-0.8.5.dist-info/RECORD
