Metadata-Version: 2.1
Name: py-progress-lib
Version: 0.8.5
Summary: Progress bar
License: MIT
Author: Drag-GameStudio
Author-email: sinica911@gmail.com
Requires-Python: >=3.12,<4.0
Classifier: License :: OSI Approved :: MIT License
Classifier: Programming Language :: Python :: 3
Classifier: Programming Language :: Python :: 3.12
Classifier: Programming Language :: Python :: 3.13
Requires-Dist: colorama (>=0.4.6,<0.5.0)
